seqeval/__init__.py
seqeval/callbacks.py
seqeval/metrics/__init__.py
seqeval/metrics/sequence_labeling.py
seqeval-0.0.10.dist-info/LICENSE
seqeval-0.0.10.dist-info/METADATA
seqeval-0.0.10.dist-info/WHEEL
seqeval-0.0.10.dist-info/top_level.txt
seqeval-0.0.10.dist-info/RECORD
